[
  {
    "monument_name": "Lumbini, the Birthplace of the Lord Buddha",
    "alternative_names": null,
    "typology": {
      "monument_type": null,
      "main_deity": "Lord Buddha",
      "religion": "Buddhism"
    },
    "location": {
      "province": null,
      "district": null,
      "municipality": null,
      "heritage_area": "Terai plains of southern Nepal",
      "tola": null
    },
    "description": "Siddhartha Gautama, the Lord Buddha, was born in 623 B.C. in the famous gardens of Lumbini, which soon became a place of pilgrimage. Among the pilgrims was the Indian emperor Ashoka, who erected one of his commemorative pillars there. The site is now being developed as a Buddhist pilgrimage centre, where the archaeological remains associated with the birth of the Lord Buddha form a central feature.\n\nThe Lord Buddha was born in 623 BC in the sacred area of Lumbini located in the Terai plains of southern Nepal, testified by the inscription on the pillar erected by the Mauryan Emperor Asoka in 249 BC. Lumbini is one of the holiest places of one of the world's great religions, and its remains contain important evidence about the nature of Buddhist pilgrimage centres from as early as the 3rd century BC.\n\nThe complex of structures within the archaeological conservation area includes the Shakya Tank; the remains within the Maya Devi Temple consisting of brick structures in a cross-wall system dating from the 3rd century BC to the present century and the sandstone Ashoka pillar with its Pali inscription in Brahmi script. Additionally there are the excavated remains of Buddhist viharas (monasteries) of the 3rd century BC to the 5th century AD and the remains of Buddhist stupas (memorial shrines) from the 3rd century BC to the 15th century AD. The site is now being developed as a Buddhist pilgrimage centre, where the archaeological remains associated with the birth of the Lord Buddha form a central feature.",
    "fun_fact": null,
    "architecture": {
      "shape": null,
      "storeys": null,
      "dimensions": null,
      "construction_materials": ["brick", "sandstone"]
    },
    "condition": {
      "status": null,
      "threats": [
        "industrial development in the region",
        "impact of visitors",
        "natural impacts including humidity"
      ]
    },
    "cultural_activities": null,
    "historical_events": [
      {
        "event": "Birth of Lord Buddha",
        "date": "623 BC"
      },
      {
        "event": "Erection of commemorative pillar by Emperor Ashoka",
        "date": "249 BC"
      },
      {
        "event": "Discovery of the Asoka pillar",
        "date": "1896"
      },
      {
        "event": "Initiation of Master Plan for site planning",
        "date": "1972-1978"
      }
    ]
  },
  {
    "monument_name": "Lumbini, the Birthplace of the Lord Buddha",
    "alternative_names": null,
    "typology": {
      "monument_type": null,
      "main_deity": "Lord Buddha",
      "religion": "Buddhism"
    },
    "location": {
      "province": null,
      "district": null,
      "municipality": null,
      "heritage_area": "Terai plains of southern Nepal",
      "tola": null
    },
    "description": "Siddhartha Gautama, the Lord Buddha, was born in 623 B.C. in the famous gardens of Lumbini, which soon became a place of pilgrimage. Among the pilgrims was the Indian emperor Ashoka, who erected one of his commemorative pillars there. The site is now being developed as a Buddhist pilgrimage centre, where the archaeological remains associated with the birth of the Lord Buddha form a central feature.\n\nThe complex of structures within the archaeological conservation area includes the Shakya Tank; the remains within the Maya Devi Temple consisting of brick structures in a cross-wall system dating from the 3rd century BC to the present century and the sandstone Ashoka pillar with its Pali inscription in Brahmi script. Additionally there are the excavated remains of Buddhist viharas (monasteries) of the 3rd century BC to the 5th century AD and the remains of Buddhist stupas (memorial shrines) from the 3rd century BC to the 15th century AD. The site is now being developed as a Buddhist pilgrimage centre, where the archaeological remains associated with the birth of the Lord Buddha form a central feature.",
    "fun_fact": null,
    "architecture": {
      "shape": null,
      "storeys": null,
      "dimensions": null,
      "construction_materials": ["brick", "sandstone"]
    },
    "condition": {
      "status": null,
      "threats": [
        "impact of visitors",
        "natural impacts including humidity",
        "industrial development in the region"
      ]
    },
    "cultural_activities": null,
    "historical_events": [
      {
        "event": "Birth of Lord Buddha",
        "date": "623 BC"
      },
      {
        "event": "Erection of Ashoka pillar",
        "date": "249 BC"
      },
      {
        "event": "Discovery of the Ashoka pillar",
        "date": "1896"
      },
      {
        "event": "Initiation of the Master Plan for the property",
        "date": "1972-1978"
      }
    ]
  },
  {
    "monument_name": "Lumbini, the Birthplace of the Lord Buddha",
    "alternative_names": null,
    "typology": {
      "monument_type": null,
      "main_deity": "Lord Buddha",
      "religion": "Buddhism"
    },
    "location": {
      "province": null,
      "district": null,
      "municipality": null,
      "heritage_area": "Terai plains of southern Nepal",
      "tola": null
    },
    "description": "Siddhartha Gautama, the Lord Buddha, was born in 623 B.C. in the famous gardens of Lumbini, which soon became a place of pilgrimage. Among the pilgrims was the Indian emperor Ashoka, who erected one of his commemorative pillars there. The site is now being developed as a Buddhist pilgrimage centre, where the archaeological remains associated with the birth of the Lord Buddha form a central feature.\n\nThe Lord Buddha was born in 623 BC in the sacred area of Lumbini located in the Terai plains of southern Nepal, testified by the inscription on the pillar erected by the Mauryan Emperor Asoka in 249 BC. Lumbini is one of the holiest places of one of the world's great religions, and its remains contain important evidence about the nature of Buddhist pilgrimage centres from as early as the 3rd century BC.\n\nThe complex of structures within the archaeological conservation area includes the Shakya Tank; the remains within the Maya Devi Temple consisting of brick structures in a cross-wall system dating from the 3rd century BC to the present century and the sandstone Ashoka pillar with its Pali inscription in Brahmi script. Additionally there are the excavated remains of Buddhist viharas (monasteries) of the 3rd century BC to the 5th century AD and the remains of Buddhist stupas (memorial shrines) from the 3rd century BC to the 15th century AD. The site is now being developed as a Buddhist pilgrimage centre, where the archaeological remains associated with the birth of the Lord Buddha form a central feature.",
    "fun_fact": null,
    "architecture": {
      "shape": null,
      "storeys": null,
      "dimensions": null,
      "construction_materials": ["brick", "sandstone"]
    },
    "condition": {
      "status": null,
      "threats": [
        "industrial development in the region",
        "natural degradation",
        "humidity",
        "impact of visitors"
      ]
    },
    "cultural_activities": null,
    "historical_events": [
      {
        "event_name": "Birth of Lord Buddha",
        "event_date": "623 B.C.",
        "event_description": "Siddhartha Gautama, the Lord Buddha, was born in the famous gardens of Lumbini."
      },
      {
        "event_name": "Erection of Ashoka Pillar",
        "event_date": "249 BC",
        "event_description": "The Mauryan Emperor Asoka erected a commemorative pillar in Lumbini."
      },
      {
        "event_name": "Discovery of Ashoka Pillar",
        "event_date": "1896",
        "event_description": "The Ashoka pillar was discovered, confirming the authenticity of the archaeological remains within the boundaries."
      },
      {
        "event_name": "Master Plan Initiation",
        "event_date": "1972-1978",
        "event_description": "The planning of the Master Plan area was initiated together with the United Nations and carried out by Prof. Kenzo Tange."
      }
    ]
  },
  {
    "monument_name": "Lumbini, the Birthplace of the Lord Buddha",
    "alternative_names": null,
    "typology": {
      "monument_type": "Buddhist pilgrimage centre",
      "main_deity": "Lord Buddha",
      "religion": "Buddhism"
    },
    "location": {
      "province": null,
      "district": null,
      "municipality": null,
      "heritage_area": "Terai plains of southern Nepal",
      "tola": null
    },
    "description": "Siddhartha Gautama, the Lord Buddha, was born in 623 B.C. in the famous gardens of Lumbini, which soon became a place of pilgrimage. Among the pilgrims was the Indian emperor Ashoka, who erected one of his commemorative pillars there. The site is now being developed as a Buddhist pilgrimage centre, where the archaeological remains associated with the birth of the Lord Buddha form a central feature.\n\nThe complex of structures within the archaeological conservation area includes the Shakya Tank; the remains within the Maya Devi Temple consisting of brick structures in a cross-wall system dating from the 3rd century BC to the present century and the sandstone Ashoka pillar with its Pali inscription in Brahmi script. Additionally there are the excavated remains of Buddhist viharas (monasteries) of the 3rd century BC to the 5th century AD and the remains of Buddhist stupas (memorial shrines) from the 3rd century BC to the 15th century AD. The site is now being developed as a Buddhist pilgrimage centre, where the archaeological remains associated with the birth of the Lord Buddha form a central feature.",
    "fun_fact": null,
    "architecture": {
      "shape": null,
      "storeys": null,
      "dimensions": null,
      "construction_materials": ["brick", "sandstone"]
    },
    "condition": {
      "status": "The integrity of Lumbini has been achieved by means of preserving the archaeological remains within the property boundary that give the property its Outstanding Universal Value. The significant attributes and elements of the property have been preserved. The buffer zone gives the property a further layer of protection. Further excavations of potential archaeological sites and appropriate protection of the archaeological remains are a high priority for the integrity of the property. The property boundary however does not include the entire archaeological site and various parts are found in the buffer zone. The entire property including the buffer zone is owned by the Government of Nepal and is being managed by the Lumbini Development Trust and therefore there is little threat of development or neglect. However the effects of industrial development in the region have been identified as a threat to the integrity of the property.",
      "threats": ["industrial development in the region"]
    },
    "cultural_activities": null,
    "historical_events": [
      {
        "event_name": "Birth of Lord Buddha",
        "event_date": "623 B.C.",
        "event_description": "Siddhartha Gautama, the Lord Buddha, was born in the famous gardens of Lumbini."
      },
      {
        "event_name": "Erection of Ashoka Pillar",
        "event_date": "249 BC",
        "event_description": "The Indian emperor Ashoka erected one of his commemorative pillars at Lumbini."
      },
      {
        "event_name": "Discovery of Ashoka Pillar",
        "event_date": "1896",
        "event_description": "The Ashoka pillar was discovered, confirming the authenticity of the archaeological remains within the boundaries."
      },
      {
        "event_name": "Master Plan Initiation",
        "event_date": "1972-1978",
        "event_description": "The planning of the Master Plan area was initiated together with the United Nations and carried out by Prof. Kenzo Tange."
      }
    ]
  },
  {
    "monument_name": "Lumbini",
    "alternative_names": ["Lumbini, the Birthplace of the Lord Buddha"],
    "typology": {
      "monument_type": null,
      "main_deity": "Lord Buddha",
      "religion": "Buddhism"
    },
    "location": {
      "province": null,
      "district": null,
      "municipality": null,
      "heritage_area": "Terai plains of southern Nepal",
      "tola": null
    },
    "description": "Siddhartha Gautama, the Lord Buddha, was born in 623 B.C. in the famous gardens of Lumbini, which soon became a place of pilgrimage. Among the pilgrims was the Indian emperor Ashoka, who erected one of his commemorative pillars there. The site is now being developed as a Buddhist pilgrimage centre, where the archaeological remains associated with the birth of the Lord Buddha form a central feature.\n\nThe Lord Buddha was born in 623 BC in the sacred area of Lumbini located in the Terai plains of southern Nepal, testified by the inscription on the pillar erected by the Mauryan Emperor Asoka in 249 BC. Lumbini is one of the holiest places of one of the world's great religions, and its remains contain important evidence about the nature of Buddhist pilgrimage centres from as early as the 3rd century BC.\n\nThe complex of structures within the archaeological conservation area includes the Shakya Tank; the remains within the Maya Devi Temple consisting of brick structures in a cross-wall system dating from the 3rd century BC to the present century and the sandstone Ashoka pillar with its Pali inscription in Brahmi script. Additionally there are the excavated remains of Buddhist viharas (monasteries) of the 3rd century BC to the 5th century AD and the remains of Buddhist stupas (memorial shrines) from the 3rd century BC to the 15th century AD. The site is now being developed as a Buddhist pilgrimage centre, where the archaeological remains associated with the birth of the Lord Buddha form a central feature.",
    "fun_fact": null,
    "architecture": {
      "shape": null,
      "storeys": null,
      "dimensions": null,
      "construction_materials": ["brick", "sandstone"]
    },
    "condition": {
      "status": null,
      "threats": [
        "impact of visitors",
        "natural impacts including humidity",
        "industrial development in the region"
      ]
    },
    "cultural_activities": null,
    "historical_events": [
      {
        "event": "Birth of Lord Buddha",
        "date": "623 BC"
      },
      {
        "event": "Erection of commemorative pillar by Emperor Ashoka",
        "date": "249 BC"
      },
      {
        "event": "Discovery of the Asoka pillar",
        "date": "1896"
      },
      {
        "event": "Initiation of Master Plan by Prof. Kenzo Tange",
        "date": "1972-1978"
      }
    ]
  }
]
